LICENSE
MANIFEST.in
README.md
setup.py
datacockpit/__init__.py
datacockpit.egg-info/PKG-INFO
datacockpit.egg-info/SOURCES.txt
datacockpit.egg-info/dependency_links.txt
datacockpit.egg-info/requires.txt
datacockpit.egg-info/top_level.txt
datacockpit/quality/__init__.py
datacockpit/quality/quality.py
datacockpit/usage/__init__.py
datacockpit/usage/usage.py
datacockpit/usage/sql_parser/__init__.py
datacockpit/usage/sql_parser/sql_parser.py
datacockpit/usage/sql_parser/sql_validator.py
datacockpit/usage/sql_parser/subquery_extractor.py