Metadata-Version: 2.1
Name: datacockpit
Version: 0.2.0
Summary: DataCockpit is a package to analyze the usage and quality metrics of your database.
Home-page: https://github.com/datacockpit-org/datacockpit
Author: Arpit Narechania
Author-email: arpitnarechania@gatech.edu
License: LICENSE
Platform: UNKNOWN
License-File: LICENSE
